dmqclib/__init__.py
dmqclib/py.typed
dmqclib/classify/__init__.py
dmqclib/classify/step1_read_input/__init__.py
dmqclib/classify/step1_read_input/dataset_all.py
dmqclib/classify/step2_calc_stats/__init__.py
dmqclib/classify/step2_calc_stats/dataset_all.py
dmqclib/classify/step3_select_profiles/__init__.py
dmqclib/classify/step3_select_profiles/dataset_all.py
dmqclib/classify/step4_select_rows/__init__.py
dmqclib/classify/step4_select_rows/dataset_all.py
dmqclib/classify/step5_extract_features/__init__.py
dmqclib/classify/step5_extract_features/dataset_all.py
dmqclib/classify/step6_classify_dataset/__init__.py
dmqclib/classify/step6_classify_dataset/dataset_all.py
dmqclib/classify/step7_concat_datasets/__init__.py
dmqclib/classify/step7_concat_datasets/concat_base.py
dmqclib/classify/step7_concat_datasets/dataset_all.py
dmqclib/common/__init__.py
dmqclib/common/base/__init__.py
dmqclib/common/base/config_base.py
dmqclib/common/base/dataset_base.py
dmqclib/common/base/feature_base.py
dmqclib/common/base/model_base.py
dmqclib/common/config/__init__.py
dmqclib/common/config/classify_config.py
dmqclib/common/config/dataset_config.py
dmqclib/common/config/training_config.py
dmqclib/common/config/yaml_schema.py
dmqclib/common/config/yaml_templates.py
dmqclib/common/loader/__init__.py
dmqclib/common/loader/classify_loader.py
dmqclib/common/loader/classify_registry.py
dmqclib/common/loader/dataset_loader.py
dmqclib/common/loader/dataset_registry.py
dmqclib/common/loader/feature_loader.py
dmqclib/common/loader/feature_registry.py
dmqclib/common/loader/model_loader.py
dmqclib/common/loader/model_registry.py
dmqclib/common/loader/training_loader.py
dmqclib/common/loader/training_registry.py
dmqclib/common/utils/__init__.py
dmqclib/common/utils/config.py
dmqclib/common/utils/file.py
dmqclib/interface/__init__.py
dmqclib/interface/classify.py
dmqclib/interface/config.py
dmqclib/interface/prepare.py
dmqclib/interface/stats.py
dmqclib/interface/train.py
dmqclib/prepare/__init__.py
dmqclib-0.6.3.dist-info/METADATA
dmqclib-0.6.3.dist-info/WHEEL
dmqclib-0.6.3.dist-info/RECORD
