Metadata-Version: 2.4
Name: dmqclib
Version: 0.6.3
Summary: This package aims to offer helper functions that simplify model building and evaluation
Author-email: Takaya Saito <takaya.saito@outlook.com>
License-Expression: MIT
Requires-Python: >=3.12
Requires-Dist: joblib>=1.4.2
Requires-Dist: jsonschema>=4.23.0
Requires-Dist: numpy>=2.2
Requires-Dist: pandas>=2.2
Requires-Dist: polars>=1.30.0
Requires-Dist: pyarrow>=19.0.0
Requires-Dist: pyyaml>=6.0.2
Requires-Dist: scikit-learn>=1.6.1
Requires-Dist: xgboost>=3.0.2
